{
  "SOURCE": "- University of Washington, Dept. of Electrical Engineering. \"Power Systems Test Case Archive\". Available at: http://www.ee.washington.edu/research/pstca/ (Accessed: Nov 14, 2020)\n\n- D. Zimmerman, C. E. Murillo-Sandnchez and R. J. Thomas. \"Matpower: Steady-state operations, planning, and analysis tools forpower systems research and education\", IEEE Transactions on PowerSystems, vol. 26, no. 1, pp. 12 \u201319, Feb. 2011. DOI: 10.1109/TPWRS.2010.2051168\n\n- A. S. Xavier, A. M. Kazachkov, O. Yurdakul, F. Qiu. \"UnitCommitment.jl: A Julia/JuMP Optimization Package for Security-Constrained Unit Commitment (Version 0.3)\". Zenodo (2022). DOI: 10.5281/zenodo.4269874\n",
  "Parameters": {
    "Version": "0.3",
    "Power balance penalty ($/MW)": 1000.0,
    "Time horizon (h)": 36
  },
  "Generators": {
    "g1": {
      "Bus": "b1",
      "Production cost curve (MW)": [
        16.901100444445653,
        95.05853244631315,
        173.2159644481807,
        251.37339645004832,
        329.53082845191585
      ],
      "Production cost curve ($)": [
        1099.68245321643,
        4045.6649041277337,
        7062.267182885995,
        10119.23331179498,
        13232.350543760054
      ],
      "Startup costs ($)": [
        19925.45,
        23327.54,
        27656.49
      ],
      "Startup delays (h)": [
        1,
        2,
        4
      ],
      "Ramp up limit (MW)": 230.67,
      "Ramp down limit (MW)": 230.67,
      "Startup limit (MW)": 230.67,
      "Shutdown limit (MW)": 230.67,
      "Minimum uptime (h)": 1,
      "Minimum downtime (h)": 1,
      "Reserve eligibility": [
        "r1"
      ],
      "Initial status (h)": 24,
      "Initial power (MW)": 172.68901
    },
    "g2": {
      "Bus": "b2",
      "Production cost curve (MW)": [
        1.7820030243269505,
        34.64443974369587,
        67.5068764630648,
        100.36931318243371,
        133.2317499018026
      ],
      "Production cost curve ($)": [
        1181.7298189539908,
        2725.6051411585095,
        4364.9798975695085,
        6325.000807532058,
        8846.656088184209
      ],
      "Startup costs ($)": [
        2824.62,
        2963.87,
        3051.8
      ],
      "Startup delays (h)": [
        1,
        2,
        4
      ],
      "Ramp up limit (MW)": 93.26,
      "Ramp down limit (MW)": 93.26,
      "Startup limit (MW)": 93.26,
      "Shutdown limit (MW)": 93.26,
      "Minimum uptime (h)": 1,
      "Minimum downtime (h)": 1,
      "Reserve eligibility": [
        "r1"
      ],
      "Initial status (h)": -24,
      "Initial power (MW)": 0.0
    },
    "g3": {
      "Bus": "b3",
      "Production cost curve (MW)": [
        1.7760700963366467,
        26.091428867729928,
        50.40678763912321,
        74.7221464105165,
        99.03750518190975
      ],
      "Production cost curve ($)": [
        928.7448021111122,
        1898.7850681728794,
        3127.236921443635,
        5257.086744039271,
        8716.662909170265
      ],
      "Startup costs ($)": [
        1590.66,
        1716.1,
        1807.08
      ],
      "Startup delays (h)": [
        1,
        2,
        4
      ],
      "Ramp up limit (MW)": 69.33,
      "Ramp down limit (MW)": 69.33,
      "Startup limit (MW)": 69.33,
      "Shutdown limit (MW)": 69.33,
      "Minimum uptime (h)": 1,
      "Minimum downtime (h)": 1,
      "Reserve eligibility": [
        "r1"
      ],
      "Initial status (h)": -24,
      "Initial power (MW)": 0.0
    },
    "g4": {
      "Bus": "b6",
      "Production cost curve (MW)": [
        1.1840214112514515,
        25.544354496853444,
        49.90468758245542,
        74.26502066805742,
        98.62535375365941
      ],
      "Production cost curve ($)": [
        1033.1272404598656,
        1938.8858471773465,
        3034.7986659739827,
        4794.049353489383,
        7572.827230104585
      ],
      "Startup costs ($)": [
        2291.06,
        2515.72,
        2846.53
      ],
      "Startup delays (h)": [
        4,
        8,
        16
      ],
      "Ramp up limit (MW)": 69.04,
      "Ramp down limit (MW)": 69.04,
      "Startup limit (MW)": 69.04,
      "Shutdown limit (MW)": 69.04,
      "Minimum uptime (h)": 4,
      "Minimum downtime (h)": 4,
      "Reserve eligibility": [
        "r1"
      ],
      "Initial status (h)": -24,
      "Initial power (MW)": 0.0
    },
    "g5": {
      "Bus": "b8",
      "Production cost curve (MW)": [
        2.804289599537525,
        26.34154651759389,
        49.87880343565026,
        73.41606035370664,
        96.95331727176298
      ],
      "Production cost curve ($)": [
        890.4143554051032,
        1940.9195390468428,
        3168.783239615191,
        5010.6668285112155,
        7763.761130042307
      ],
      "Startup costs ($)": [
        1975.65,
        2337.65,
        2804.43
      ],
      "Startup delays (h)": [
        1,
        2,
        4
      ],
      "Ramp up limit (MW)": 67.87,
      "Ramp down limit (MW)": 67.87,
      "Startup limit (MW)": 67.87,
      "Shutdown limit (MW)": 67.87,
      "Minimum uptime (h)": 1,
      "Minimum downtime (h)": 1,
      "Reserve eligibility": [
        "r1"
      ],
      "Initial status (h)": -24,
      "Initial power (MW)": 0.0
    }
  },
  "Transmission lines": {
    "l1": {
      "Source bus": "b1",
      "Target bus": "b2",
      "Reactance (ohms)": 0.05917,
      "Susceptance (S)": 29.49686
    },
    "l2": {
      "Source bus": "b1",
      "Target bus": "b5",
      "Reactance (ohms)": 0.22304,
      "Susceptance (S)": 7.82518
    },
    "l3": {
      "Source bus": "b2",
      "Target bus": "b3",
      "Reactance (ohms)": 0.19797,
      "Susceptance (S)": 8.81613
    },
    "l4": {
      "Source bus": "b2",
      "Target bus": "b4",
      "Reactance (ohms)": 0.17632,
      "Susceptance (S)": 9.89865
    },
    "l5": {
      "Source bus": "b2",
      "Target bus": "b5",
      "Reactance (ohms)": 0.17388,
      "Susceptance (S)": 10.03755
    },
    "l6": {
      "Source bus": "b3",
      "Target bus": "b4",
      "Reactance (ohms)": 0.17103,
      "Susceptance (S)": 10.20481
    },
    "l7": {
      "Source bus": "b4",
      "Target bus": "b5",
      "Reactance (ohms)": 0.04211,
      "Susceptance (S)": 41.44691
    },
    "l8": {
      "Source bus": "b4",
      "Target bus": "b7",
      "Reactance (ohms)": 0.20912,
      "Susceptance (S)": 8.34607
    },
    "l9": {
      "Source bus": "b4",
      "Target bus": "b9",
      "Reactance (ohms)": 0.55618,
      "Susceptance (S)": 3.13807
    },
    "l10": {
      "Source bus": "b5",
      "Target bus": "b6",
      "Reactance (ohms)": 0.25202,
      "Susceptance (S)": 6.92536
    },
    "l12": {
      "Source bus": "b6",
      "Target bus": "b12",
      "Reactance (ohms)": 0.25581,
      "Susceptance (S)": 6.82276
    },
    "l13": {
      "Source bus": "b6",
      "Target bus": "b13",
      "Reactance (ohms)": 0.13027,
      "Susceptance (S)": 13.39778
    },
    "l14": {
      "Source bus": "b7",
      "Target bus": "b8",
      "Reactance (ohms)": 0.17615,
      "Susceptance (S)": 9.9082
    },
    "l15": {
      "Source bus": "b7",
      "Target bus": "b9",
      "Reactance (ohms)": 0.11001,
      "Susceptance (S)": 15.86519
    },
    "l16": {
      "Source bus": "b9",
      "Target bus": "b10",
      "Reactance (ohms)": 0.0845,
      "Susceptance (S)": 20.65478
    },
    "l17": {
      "Source bus": "b9",
      "Target bus": "b14",
      "Reactance (ohms)": 0.27038,
      "Susceptance (S)": 6.4551
    },
    "l18": {
      "Source bus": "b10",
      "Target bus": "b11",
      "Reactance (ohms)": 0.19207,
      "Susceptance (S)": 9.08694
    },
    "l19": {
      "Source bus": "b12",
      "Target bus": "b13",
      "Reactance (ohms)": 0.19988,
      "Susceptance (S)": 8.73189
    },
    "l20": {
      "Source bus": "b13",
      "Target bus": "b14",
      "Reactance (ohms)": 0.34802,
      "Susceptance (S)": 5.01503
    }
  },
  "Contingencies": {
    "c1": {
      "Affected lines": [
        "l1"
      ]
    },
    "c2": {
      "Affected lines": [
        "l2"
      ]
    },
    "c3": {
      "Affected lines": [
        "l3"
      ]
    },
    "c4": {
      "Affected lines": [
        "l4"
      ]
    },
    "c5": {
      "Affected lines": [
        "l5"
      ]
    },
    "c6": {
      "Affected lines": [
        "l6"
      ]
    },
    "c7": {
      "Affected lines": [
        "l7"
      ]
    },
    "c8": {
      "Affected lines": [
        "l8"
      ]
    },
    "c9": {
      "Affected lines": [
        "l9"
      ]
    },
    "c10": {
      "Affected lines": [
        "l10"
      ]
    },
    "c12": {
      "Affected lines": [
        "l12"
      ]
    },
    "c13": {
      "Affected lines": [
        "l13"
      ]
    },
    "c15": {
      "Affected lines": [
        "l15"
      ]
    },
    "c16": {
      "Affected lines": [
        "l16"
      ]
    },
    "c17": {
      "Affected lines": [
        "l17"
      ]
    },
    "c18": {
      "Affected lines": [
        "l18"
      ]
    },
    "c19": {
      "Affected lines": [
        "l19"
      ]
    },
    "c20": {
      "Affected lines": [
        "l20"
      ]
    }
  },
  "Buses": {
    "b1": {
      "Load (MW)": 0.0
    },
    "b2": {
      "Load (MW)": [
        14.46854,
        13.75404,
        13.43388,
        13.14021,
        13.06831,
        13.23482,
        13.98489,
        14.63505,
        15.84001,
        17.21904,
        17.78216,
        18.04329,
        18.15682,
        18.07659,
        18.25824,
        18.55343,
        19.14606,
        19.54116,
        21.61879,
        21.61274,
        19.83937,
        18.49666,
        17.23872,
        15.65457,
        15.23072,
        14.54953,
        14.07799,
        14.04317,
        14.53287,
        15.89753,
        19.59035,
        20.79455,
        20.43125,
        21.4871,
        21.9662,
        21.66799
      ]
    },
    "b3": {
      "Load (MW)": [
        62.80813,
        59.70649,
        58.31667,
        57.04184,
        56.72971,
        57.45255,
        60.70861,
        63.53097,
        68.76169,
        74.74811,
        77.19262,
        78.32616,
        78.81901,
        78.47073,
        79.25928,
        80.54068,
        83.11333,
        84.82843,
        93.84749,
        93.8212,
        86.12297,
        80.29426,
        74.83354,
        67.95671,
        66.11676,
        63.15969,
        61.11274,
        60.9616,
        63.08741,
        69.0114,
        85.04199,
        90.26943,
        88.69233,
        93.27579,
        95.35559,
        94.06105
      ]
    },
    "b4": {
      "Load (MW)": [
        31.87079,
        30.29692,
        29.59169,
        28.9448,
        28.78641,
        29.1532,
        30.80543,
        32.23758,
        34.89181,
        37.92951,
        39.16993,
        39.74512,
        39.99521,
        39.81848,
        40.21862,
        40.86884,
        42.17428,
        43.04457,
        47.62112,
        47.60779,
        43.70146,
        40.74379,
        37.97286,
        34.48334,
        33.54969,
        32.04918,
        31.0105,
        30.93381,
        32.01251,
        35.01852,
        43.15294,
        45.80551,
        45.00524,
        47.33103,
        48.38638,
        47.72949
      ]
    },
    "b5": {
      "Load (MW)": [
        5.06732,
        4.81708,
        4.70495,
        4.6021,
        4.57692,
        4.63524,
        4.89793,
        5.12564,
        5.54765,
        6.03063,
        6.22785,
        6.31931,
        6.35907,
        6.33097,
        6.39459,
        6.49797,
        6.70553,
        6.84391,
        7.57156,
        7.56944,
        6.94835,
        6.47809,
        6.03753,
        5.48271,
        5.33426,
        5.09569,
        4.93054,
        4.91835,
        5.08985,
        5.5678,
        6.86114,
        7.28288,
        7.15564,
        7.52543,
        7.69323,
        7.58879
      ]
    },
    "b6": {
      "Load (MW)": [
        7.46763,
        7.09886,
        6.93362,
        6.78205,
        6.74493,
        6.83088,
        7.21801,
        7.55358,
        8.17549,
        8.88725,
        9.17789,
        9.31266,
        9.37126,
        9.32985,
        9.42361,
        9.57596,
        9.88184,
        10.08576,
        11.15809,
        11.15496,
        10.23967,
        9.54666,
        8.89741,
        8.07978,
        7.86102,
        7.50943,
        7.26606,
        7.24809,
        7.50084,
        8.20518,
        10.11115,
        10.73267,
        10.54516,
        11.09011,
        11.3374,
        11.18348
      ]
    },
    "b7": {
      "Load (MW)": 0.0
    },
    "b8": {
      "Load (MW)": 0.0
    },
    "b9": {
      "Load (MW)": [
        19.66921,
        18.69789,
        18.26265,
        17.86342,
        17.76567,
        17.99204,
        19.01172,
        19.89558,
        21.53365,
        23.40838,
        24.17391,
        24.52889,
        24.68324,
        24.57417,
        24.82111,
        25.2224,
        26.02806,
        26.56517,
        29.38961,
        29.38137,
        26.97057,
        25.14523,
        23.43513,
        21.28156,
        20.70535,
        19.77931,
        19.13828,
        19.09095,
        19.75667,
        21.61185,
        26.63205,
        28.26909,
        27.7752,
        29.21057,
        29.86189,
        29.45649
      ]
    },
    "b10": {
      "Load (MW)": [
        6.00078,
        5.70444,
        5.57166,
        5.44986,
        5.42004,
        5.4891,
        5.80019,
        6.06984,
        6.56959,
        7.14154,
        7.37509,
        7.48339,
        7.53048,
        7.4972,
        7.57254,
        7.69497,
        7.94076,
        8.10463,
        8.96632,
        8.96381,
        8.22831,
        7.67143,
        7.1497,
        6.49268,
        6.31689,
        6.03437,
        5.8388,
        5.82436,
        6.02746,
        6.59345,
        8.12503,
        8.62447,
        8.47379,
        8.9117,
        9.11041,
        8.98672
      ]
    },
    "b11": {
      "Load (MW)": [
        2.33364,
        2.21839,
        2.16676,
        2.11939,
        2.10779,
        2.13465,
        2.25563,
        2.36049,
        2.55484,
        2.77727,
        2.86809,
        2.91021,
        2.92852,
        2.91558,
        2.94488,
        2.99249,
        3.08807,
        3.1518,
        3.4869,
        3.48593,
        3.1999,
        2.98333,
        2.78044,
        2.52493,
        2.45657,
        2.3467,
        2.27064,
        2.26503,
        2.34401,
        2.56412,
        3.15973,
        3.35396,
        3.29536,
        3.46566,
        3.54294,
        3.49484
      ]
    },
    "b12": {
      "Load (MW)": [
        4.06719,
        3.86634,
        3.77634,
        3.69379,
        3.67358,
        3.72039,
        3.93124,
        4.114,
        4.45272,
        4.84038,
        4.99867,
        5.07208,
        5.10399,
        5.08144,
        5.1325,
        5.21548,
        5.38207,
        5.49314,
        6.07717,
        6.07547,
        5.57696,
        5.19952,
        4.84591,
        4.40059,
        4.28145,
        4.08996,
        3.95741,
        3.94762,
        4.08528,
        4.46889,
        5.50697,
        5.84547,
        5.74335,
        6.04015,
        6.17483,
        6.091
      ]
    },
    "b13": {
      "Load (MW)": [
        9.00116,
        8.55666,
        8.35748,
        8.17479,
        8.13005,
        8.23365,
        8.70028,
        9.10476,
        9.85438,
        10.71231,
        11.06264,
        11.22509,
        11.29572,
        11.24581,
        11.35881,
        11.54245,
        11.91115,
        12.15694,
        13.44948,
        13.44571,
        12.34246,
        11.50714,
        10.72455,
        9.73902,
        9.47533,
        9.05155,
        8.7582,
        8.73654,
        9.04119,
        9.89017,
        12.18755,
        12.9367,
        12.71068,
        13.36755,
        13.66561,
        13.48009
      ]
    },
    "b14": {
      "Load (MW)": [
        9.93462,
        9.44402,
        9.22419,
        9.02254,
        8.97317,
        9.08751,
        9.60253,
        10.04895,
        10.87632,
        11.82322,
        12.20987,
        12.38917,
        12.46713,
        12.41204,
        12.53677,
        12.73945,
        13.14638,
        13.41766,
        14.84424,
        14.84008,
        13.62242,
        12.70047,
        11.83673,
        10.74899,
        10.45796,
        9.99023,
        9.66645,
        9.64255,
        9.97879,
        10.91582,
        13.45144,
        14.27829,
        14.02883,
        14.75381,
        15.08278,
        14.87802
      ]
    }
  },
  "Reserves": {
    "r1": {
      "Type": "Spinning",
      "Amount (MW)": [
        3.45,
        3.28,
        3.21,
        3.14,
        3.12,
        3.16,
        3.34,
        3.49,
        3.78,
        4.11,
        4.24,
        4.31,
        4.33,
        4.32,
        4.36,
        4.43,
        4.57,
        4.66,
        5.16,
        5.16,
        4.74,
        4.42,
        4.12,
        3.74,
        3.64,
        3.47,
        3.36,
        3.35,
        3.47,
        3.79,
        4.68,
        4.96,
        4.88,
        5.13,
        5.24,
        5.17
      ]
    }
  }
}